[
    {
        "Pregunta": "¿Como se llama la madre de Goku?",
        "Respuestas": [
            "Gine",
            "Apple",
            "Nuts"
        ],
        "IndiceRespuestaCorrecta": 0
    },
    {
        "Pregunta": "¿Quien mato a Nappa?",
        "Respuestas": [
            "Vegeta",
            "Goku",
            "Krillin"
        ],
        "IndiceRespuestaCorrecta": 0
    },
    {
        "Pregunta": "¿Como se llama la reencarnacion buena de Majin Boo?",
        "Respuestas": [
            "Uub",
            "Pan",
            "Bra"
        ],
        "IndiceRespuestaCorrecta": 0
    },
    {
        "Pregunta": "¿Quien mato al padre de Goku?",
        "Respuestas": [
            "Freezer",
            "Rey Vegeta",
            "Bills"
        ],
        "IndiceRespuestaCorrecta": 0
    },
    {
        "Pregunta": "¿Quien muere para que Gohan se transforme en Ssj 2?",
        "Respuestas": [
            "Androide 16",
            "Krillin",
            "Piccolo"
        ],
        "IndiceRespuestaCorrecta": 0
    },
    {
        "Pregunta": "De las esferas del dragon, ¿Cual es el numero de la suerte de Goku?",
        "Respuestas": [
            "7",
            "2",
            "4"
        ],
        "IndiceRespuestaCorrecta": 2
    },
    {
        "Pregunta": "¿Como se llama el dragon en el planeta Namekusei?",
        "Respuestas": [
            "Shenron",
            "Porunga",
            "Omega Porunga"
        ],
        "IndiceRespuestaCorrecta": 1
    },
    {
        "Pregunta": "¿Quien derroto al Androide 19?",
        "Respuestas": [
            "Trunks",
            "Goku",
            "Vegeta"
        ],
        "IndiceRespuestaCorrecta": 2
    },
    {
        "Pregunta": "¿Cuantas veces le cortaron la cola a Gohan?",
        "Respuestas": [
            "1 Vez",
            "2 Veces",
            "Nunca le cortaron la cola"
        ],
        "IndiceRespuestaCorrecta": 2
    },
    {
        "Pregunta": "¿Cuál es el seudónimo que utiliza Píccoro para registrarse en el torneo de las artes marciales?",
        "Respuestas": [
            "Majunia",
            "Daimakú",
            "Ninguno"
        ],
        "IndiceRespuestaCorrecta": 0
    },
    {
        "Pregunta": "¿Quien secuestra a Gohan?",
        "Respuestas": [
            "Raditz",
            "Cell",
            "Vegeta"
        ],
        "IndiceRespuestaCorrecta": 0
    },
    {
        "Pregunta": "¿Cuantas veces muere Goku?",
        "Respuestas": [
            "1 Vez",
            "2 Veces",
            "3 Veces"
        ],
        "IndiceRespuestaCorrecta": 1
    },
    {
        "Pregunta": "¿Como se llama la nieta de Goku y Milk?",
        "Respuestas": [
            "Asta",
            "Pan",
            "Apu"
        ],
        "IndiceRespuestaCorrecta": 1
    },
    {
        "Pregunta": "¿Como se llama el maestro ermitanio que vive en una torre?",
        "Respuestas": [
            "Maestro Karin",
            "Kamisama",
            "Gran Patriarca"
        ],
        "IndiceRespuestaCorrecta": 0
    },
    {
        "Pregunta": "¿De quien es la tecnica Kikoho?",
        "Respuestas": [
            "Krillin",
            "Yamcha",
            "Tenshinhan"
        ],
        "IndiceRespuestaCorrecta": 2
    },
    {
        "Pregunta": "¿Cuantos capitulos tiene Dragon Ball Z?",
        "Respuestas": [
            "194 Capitulos",
            "290 Capitulos",
            "291 Capitulos"
        ],
        "IndiceRespuestaCorrecta": 2
    },
    {
        "Pregunta": "¿Cuantas transformaciones tiene Majin Buu, contando su reencarnacion?",
        "Respuestas": [
            "7 Transformaciones",
            "5 Transformaciones",
            "9 Transformaciones"
        ],
        "IndiceRespuestaCorrecta": 2
    },
    {
        "Pregunta": "¿Que es lo que mas teme Goku?",
        "Respuestas": [
            "Milk",
            "Inyecciones",
            "Broly"
        ],
        "IndiceRespuestaCorrecta": 1
    },
    {
        "Pregunta": "¿Cual es la unica tecnica propia de Goku?",
        "Respuestas": [
            "Genkidama",
            "Kamehameha",
            "Puño de Dragon"
        ],
        "IndiceRespuestaCorrecta": 2
    },
    {
        "Pregunta": "¿Quien le dio la espada a Trunks?",
        "Respuestas": [
            "Tapion",
            "Vegeta",
            "Goten"
        ],
        "IndiceRespuestaCorrecta": 0
    },
    {
        "Pregunta": "¿Cuantos años tenia Gohan cuando Piccoro lo llevo a entrenar?",
        "Respuestas": [
            "4 Años",
            "5 Años",
            "6 Años"
        ],
        "IndiceRespuestaCorrecta": 0
    },
    {
        "Pregunta": "¿Cual de todos los villanos no mato a Krillin?",
        "Respuestas": [
            "Freezer",
            "Cell",
            "Majin Buu"
        ],
        "IndiceRespuestaCorrecta": 1
    },
    {
        "Pregunta": "¿Cuanto tiempo tardo el Maestro Roshi en perfeccionar el Kamehameha?",
        "Respuestas": [
            "50 Años",
            "3 Meses",
            "30 Años"
        ],
        "IndiceRespuestaCorrecta": 0
    },
    {
        "Pregunta": "¿Quien derrota a Cell?",
        "Respuestas": [
            "Goku",
            "Gohan",
            "Vegeta"
        ],
        "IndiceRespuestaCorrecta": 1
    },
    {
        "Pregunta": "¿Cual de los siguientes personajes es el amigo de Buu?",
        "Respuestas": [
            "Mr Satan",
            "Babidi",
            "Goten"
        ],
        "IndiceRespuestaCorrecta": 0
    },
    {
        "Pregunta": "¿Que usan los guerreros z para recuperar su fuerza?",
        "Respuestas": [
            "Semilla del ermitanio",
            "Medicina",
            "Agua"
        ],
        "IndiceRespuestaCorrecta": 0
    },
    {
        "Pregunta": "¿Quien destruye el planeta Vegeta?",
        "Respuestas": [
            "Turles",
            "Freezer",
            "Bills"
        ],
        "IndiceRespuestaCorrecta": 1
    },
    {
        "Pregunta": "¿Cuál es el nombre del planeta natal de Goku?",
        "Respuestas": [
            "Tierra",
            "Vegeta",
            "Marte"
        ],
        "IndiceRespuestaCorrecta": 1
    },
    {
        "Pregunta": "¿Quién es el hermano mayor de Goku?",
        "Respuestas": [
            "Turles",
            "Raditz",
            "Ambos"
        ],
        "IndiceRespuestaCorrecta": 1
    }
]